pcapparser/__init__.py
pcapparser/__main__.py
PcapParser-0.1.1.dist-info/METADATA
PcapParser-0.1.1.dist-info/WHEEL
PcapParser-0.1.1.dist-info/entry_points.txt
PcapParser-0.1.1.dist-info/top_level.txt
PcapParser-0.1.1.dist-info/RECORD
