Metadata-Version: 2.1
Name: PcapParser
Version: 0.1.1
Summary: Extract rtmp links from pcap file
Author-email: mokurin000 <1348292515a@gmail.com>
License: MIT
Requires-Python: >=3.12
Requires-Dist: dpkt >=1.9.8
